pyxshells.py
xsplot.py
pyxshells-2.8.dist-info/METADATA
pyxshells-2.8.dist-info/WHEEL
pyxshells-2.8.dist-info/top_level.txt
pyxshells-2.8.dist-info/RECORD
