Metadata-Version: 2.1
Name: pyxshells
Version: 2.8
Summary: python tools for handling field output of xshells code
Home-page: https://nschaeff.bitbucket.io/xshells
Author: Nathanael Schaeffer
Author-email: Nathanael Schaeffer <nathanael.schaeffer@gmail.com>
Project-URL: Homepage, https://nschaeff.bitbucket.io/xshells
Project-URL: Documentation, https://nschaeff.bitbucket.io/xshells/manual.html
Project-URL: Repository, https://bitbucket.org/nschaeff/xshells/
Project-URL: Changelog, https://bitbucket.org/nschaeff/xshells/src/master/CHANGELOG.md
Classifier: Programming Language :: Python
Classifier: License :: OSI Approved :: CEA CNRS Inria Logiciel Libre License, version 2.1 (CeCILL-2.1)
Classifier: Intended Audience :: Science/Research
Classifier: Development Status :: 5 - Production/Stable
Classifier: Topic :: Scientific/Engineering
Requires: numpy
Requires: matplotlib
Requires: shtns
Requires-Python: >=3.2
Requires-Dist: numpy
Requires-Dist: matplotlib
Requires-Dist: shtns
